pytower/manage.py
pytower/pytower/__init__.py
pytower/pytower/asgi.py
pytower/pytower/settings.py
pytower/pytower/urls.py
pytower/pytower/wsgi.py
moulder-0.0.1.dev1.dist-info/LICENSE
moulder-0.0.1.dev1.dist-info/METADATA
moulder-0.0.1.dev1.dist-info/WHEEL
moulder-0.0.1.dev1.dist-info/top_level.txt
moulder-0.0.1.dev1.dist-info/RECORD
