Metadata-Version: 2.1
Name: moulder
Version: 0.0.1.dev1
Summary: build and deploy Pythonic apps
Author-email: Salman Mohammadi <salman@pytower.com>
Project-URL: Homepage, https://pytower.com
Project-URL: Source Code, https://codeberg.org/pytower/pytower
Project-URL: Bug Tracker, https://codeberg.org/pytower/pytower/issues
Project-URL: Documentation, https://docs.pytower.com
Classifier: Programming Language :: Python :: 3
Classifier: License :: OSI Approved :: GNU Affero General Public License v3 or later (AGPLv3+)
Classifier: Operating System :: POSIX :: Linux
Classifier: Development Status :: 2 - Pre-Alpha
Classifier: Environment :: Web Environment
Classifier: Intended Audience :: Developers
Requires-Python: >=3.8
License-File: LICENSE
Requires-Dist: django <4,>=3.2
Requires-Dist: djangorestframework
Requires-Dist: dj-database-url
Requires-Dist: mysqlclient
Provides-Extra: dev
Requires-Dist: pylint ; extra == 'dev'
Requires-Dist: pylint-django ; extra == 'dev'
Requires-Dist: flake8 ; extra == 'dev'
Requires-Dist: isort ; extra == 'dev'
